dot_follow/__init__.py
dot_follow/dot_app.py
BlightStalker-0.2.dist-info/METADATA
BlightStalker-0.2.dist-info/WHEEL
BlightStalker-0.2.dist-info/top_level.txt
BlightStalker-0.2.dist-info/RECORD
