Metadata-Version: 2.1
Name: BlightStalker
Version: 0.2
Requires-Dist: tk
